gradio_rangeslider/__init__.py
gradio_rangeslider/rangeslider.py
gradio_rangeslider/rangeslider.pyi
gradio_rangeslider/templates/component/index.js
gradio_rangeslider/templates/component/style.css
gradio_rangeslider/templates/example/index.js
gradio_rangeslider/templates/example/style.css
gradio_rangeslider-0.0.7.dist-info/METADATA
gradio_rangeslider-0.0.7.dist-info/WHEEL
gradio_rangeslider-0.0.7.dist-info/licenses/LICENSE
gradio_rangeslider-0.0.7.dist-info/RECORD
