Metadata-Version: 2.3
Name: gradio_rangeslider
Version: 0.0.7
Summary: 🛝 Slider component for selecting a range of values
Project-URL: repository, https://github.com/freddyaboulton/gradio-range-slider
Project-URL: space, https://huggingface.co/spaces/freddyaboulton/gradio_rangeslider
Author-email: YOUR NAME <YOUREMAIL@domain.com>
License-Expression: Apache-2.0
License-File: LICENSE
Keywords: filtering,forms,gradio-custom-component,gradio-template-Slider,leaderboards,slider
Classifier: Development Status :: 3 - Alpha
Classifier: Operating System :: OS Independent
Classifier: Programming Language :: Python :: 3
Classifier: Programming Language :: Python :: 3 :: Only
Classifier: Programming Language :: Python :: 3.8
Classifier: Programming Language :: Python :: 3.9
Classifier: Programming Language :: Python :: 3.10
Classifier: Programming Language :: Python :: 3.11
Classifier: Topic :: Scientific/Engineering
Classifier: Topic :: Scientific/Engineering :: Artificial Intelligence
Classifier: Topic :: Scientific/Engineering :: Visualization
Requires-Python: >=3.8
Requires-Dist: gradio<6.0,>=4.0
Provides-Extra: dev
Requires-Dist: build; extra == 'dev'
Requires-Dist: twine; extra == 'dev'
